{
    "Keras-2.2.5 Relu Activation":{
        "prefix":"!relu",
        "body":[
            "from tensorflow.keras import activations",
            "activations.relu(x, alpha=0.0, max_value=None, threshold=0)"
        ]
    },
    "Keras-2.2.5 Softmax Activation":{
        "prefix":"!softmax",
        "body":[
            "from tensorflow.keras import activations",
            "activations.softmax(x, axis=-1)"
        ]
    },
    "Keras-2.2.5 Sigmoid Activation":{
        "prefix":"!sigmoid",
        "body":[
            "from tensorflow.keras import activations",
            "activations.sigmoid(x)"
        ]
    },
    "Keras-2.2.5 tanh Activation":{
        "prefix":"!tanh",
        "body":[
            "from tensorflow.keras import activations",
            "activations.tanh(x)"
        ]
    },
    "Keras-2.2.5 Softsign Activation":{
        "prefix":"!softsign",
        "body":[
            "from tensorflow.keras import activations",
            "activations.softsign(x)"
        ]
    }
    

}